Metadata-Version: 2.1
Name: macrometa-target-mongo
Version: 1.0.0
Summary: Macrometa connector for writing data into MongoDB, can be used as a target for any Data Mesh Integration.
License: Apache-2.0
Keywords: ELT,Connectors,Workflows,Macrometa,Target,MongoDB
Author: Macrometa
Author-email: product@macrometa.com
Requires-Python: >=3.8.1,<3.11
Classifier: License :: OSI Approved :: Apache Software License
Classifier: Operating System :: OS Independent
Classifier: Programming Language :: Python :: 3
Classifier: Programming Language :: Python :: 3.9
Classifier: Programming Language :: Python :: 3.10
Classifier: Programming Language :: Python :: 3
Classifier: Programming Language :: Python :: 3.9
Requires-Dist: adjust-precision-for-schema (==0.3.4)
Requires-Dist: c8connector (>=0.0.29)
Requires-Dist: pipelinewise-singer-python (==1.2.0)
Requires-Dist: prometheus-client (==0.16.0)
Requires-Dist: pymongo[srv] (>=4.0,<5.0)
Requires-Dist: requests (>=2.25.1,<3.0.0)
Project-URL: Bug Tracker, https://github.com/Macrometacorp/macrometa-target-mongo/issues
Project-URL: Homepage, https://www.macrometa.com/
